commlink/__init__.py
commlink/publisher.py
commlink/py.typed
commlink/rpc_client.py
commlink/rpc_server.py
commlink/subscriber.py
commlink-0.1.5.dist-info/licenses/LICENSE
commlink-0.1.5.dist-info/METADATA
commlink-0.1.5.dist-info/WHEEL
commlink-0.1.5.dist-info/top_level.txt
commlink-0.1.5.dist-info/RECORD
