Metadata-Version: 2.4
Name: commlink
Version: 0.1.5
Summary: ZeroMQ-based publisher/subscriber and RPC utilities
Author: Commlink Maintainers
License: MIT License
Keywords: zeromq,messaging,rpc,pubsub
Classifier: Programming Language :: Python :: 3
Classifier: Programming Language :: Python :: 3 :: Only
Classifier: Programming Language :: Python :: 3.9
Classifier: Programming Language :: Python :: 3.10
Classifier: Programming Language :: Python :: 3.11
Classifier: Programming Language :: Python :: 3.12
Classifier: License :: OSI Approved :: MIT License
Classifier: Topic :: Communications
Classifier: Topic :: System :: Networking
Requires-Python: >=3.9
License-File: LICENSE
Requires-Dist: pyzmq>=25.1
Provides-Extra: test
Requires-Dist: pytest>=7; extra == "test"
Dynamic: license-file
